<?xml version="1.0" encoding="GB2312"?>
<Data>
	<Object>
		<ID>1</ID>
		<Config>assets/map/map1.xml</Config>
		<Battle>0</Battle>
		<Name>篮球场</Name>
		<InvisibleMineScript>InvisibleMineScript1</InvisibleMineScript>
		<InitMapScript>InitMapScript1</InitMapScript>
	</Object>
	<Object>
		<ID>2</ID>
		<Config>assets/map/map2.xml</Config>
		<Battle>1</Battle>
		<Name>篮球场战斗地图</Name>
		<InitMapScript>InitMapScript2</InitMapScript>
	</Object>
	<Object>
		<ID>3</ID>
		<Config>assets/map/map3.xml</Config>
		<Battle>0</Battle>
		<Name>上帝街</Name>
		<InitMapScript>InitMapScript3</InitMapScript>
	</Object>
	<Object>
		<ID>4</ID>
		<Config>assets/map/map4.xml</Config>
		<Battle>0</Battle>
		<Name>西街</Name>
		<InvisibleMineScript>InvisibleMineScript4</InvisibleMineScript>
		<InitMapScript>InitMapScript4</InitMapScript>
	</Object>
	<Object>
		<ID>5</ID>
		<Config>assets/map/map5.xml</Config>
		<Battle>0</Battle>
		<Name>东街</Name>
		<InvisibleMineScript>InvisibleMineScript5</InvisibleMineScript>
		<InitMapScript>InitMapScript5</InitMapScript>
	</Object>
	<Object>
		<ID>6</ID>
		<Config>assets/map/map6.xml</Config>
		<Battle>0</Battle>
		<Name>Z33高校</Name>
		<InitMapScript>InitMapScript6</InitMapScript>
	</Object>
	<Object>
		<ID>7</ID>
		<Config>assets/map/map7.xml</Config>
		<Battle>0</Battle>
		<Name>红唇后巷东</Name>
		<InvisibleMineScript>InvisibleMineScript7</InvisibleMineScript>
		<InitMapScript>InitMapScript7</InitMapScript>
	</Object>
	<Object>
		<ID>8</ID>
		<Config>assets/map/map8.xml</Config>
		<Battle>0</Battle>
		<Name>红唇后巷西</Name>
		<InvisibleMineScript>InvisibleMineScript8</InvisibleMineScript>
		<InitMapScript>InitMapScript8</InitMapScript>
	</Object>
	<Object>
		<ID>9</ID>
		<Config>assets/map/map9.xml</Config>
		<Battle>0</Battle>
		<Name>遗忘海滩</Name>
		<InvisibleMineScript>InvisibleMineScript9</InvisibleMineScript>
		<InitMapScript>InitMapScript9</InitMapScript>
	</Object>
</Data>